jwt_auth/__init__.py
jwt_auth/config.py
jwt_auth/constants.py
jwt_auth/exceptions.py
jwt_auth/generator.py
jwt_auth/models.py
jwt_auth/parser.py
jwt_auth/utils.py
jwt_auth/validator.py
jwt_auth_module-0.1.1.dist-info/METADATA
jwt_auth_module-0.1.1.dist-info/WHEEL
jwt_auth_module-0.1.1.dist-info/top_level.txt
jwt_auth_module-0.1.1.dist-info/RECORD
