Metadata-Version: 2.4
Name: jwt-auth-module
Version: 0.1.1
Summary: JWT authentication library for Python
Author: CubedM
License-Expression: MIT
Project-URL: Homepage, https://github.com/cubedm/jwt-auth-modules
Project-URL: Repository, https://github.com/cubedm/jwt-auth-modules
Project-URL: Documentation, https://github.com/cubedm/jwt-auth-modules/tree/main/jwt-python
Keywords: jwt,authentication,token,security
Classifier: Development Status :: 3 - Alpha
Classifier: Intended Audience :: Developers
Classifier: Programming Language :: Python :: 3
Classifier: Programming Language :: Python :: 3.9
Classifier: Programming Language :: Python :: 3.10
Classifier: Programming Language :: Python :: 3.11
Classifier: Programming Language :: Python :: 3.12
Requires-Python: >=3.9
Requires-Dist: pyjwt>=2.8.0
Provides-Extra: dev
Requires-Dist: pytest>=7.4.0; extra == "dev"
Requires-Dist: pytest-cov>=4.1.0; extra == "dev"
Requires-Dist: mypy>=1.5.0; extra == "dev"
Requires-Dist: black>=23.7.0; extra == "dev"
Requires-Dist: ruff>=0.0.285; extra == "dev"
